mcp_server_iris/__init__.py
mcp_server_iris/__main__.py
mcp_server_iris/interoperability.py
mcp_server_iris/mcpserver.py
mcp_server_iris/server.py
mcp_server_iris/sql.py
mcp_server_iris/tools.py
mcp_server_iris-0.3.0.dist-info/METADATA
mcp_server_iris-0.3.0.dist-info/WHEEL
mcp_server_iris-0.3.0.dist-info/entry_points.txt
mcp_server_iris-0.3.0.dist-info/licenses/LICENSE
mcp_server_iris-0.3.0.dist-info/RECORD
