Metadata-Version: 2.4
Name: mcp-server-iris
Version: 0.3.0
Summary: A Model Context Protocol server for InterSystems IRIS.
Author: CaretDev Corp.
Maintainer-email: Dmitry Maslennikov <dmitry@caretdev.com>
License: MIT
License-File: LICENSE
Keywords: automation,iris,llm,mcp
Classifier: Development Status :: 4 - Beta
Classifier: Intended Audience :: Developers
Classifier: License :: OSI Approved :: MIT License
Classifier: Programming Language :: Python :: 3
Classifier: Programming Language :: Python :: 3.10
Requires-Python: >=3.10
Requires-Dist: intersystems-irispython>=5.1.0
Requires-Dist: mcp[cli]>=1.2.0
Requires-Dist: starlette>=0.36.0
Requires-Dist: uvicorn>=0.27.0
